{
    "name": "双联380mmSKC主炮",
    "alias": [],
    "rarity": 2,
    "level": "T2",
    "type": "战列炮",
    "attrs": {
        "伤害": {
            "初始": "53×2",
            "强化+10(满)": "122×2"
        },
        "标准射速": {
            "初始": "24.63s/轮",
            "强化+10(满)": "19.36s/轮"
        },
        "炮击": "25",
        "弹药": {
            "备注": "穿甲弹",
            "飞行速度": "12",
            "对甲比例": "45-130-110",
            "伤害范围": "15",
            "散布范围": "16*16"
        },
        "装备参数": {
            "索敌范围": "50-200",
            "索敌角度": "50",
            "所属阵营": "铁血",
            "伤害修正比例": "110%",
            "伤害属性类型": "炮击",
            "属性效率": "100%"
        }
    },
    "suit_type": [
        "战列",
        "战巡",
        "重炮",
        "航战"
    ],
    "img_url": ""
}