{
    "name": "链式装弹机",
    "alias": [],
    "rarity": 2,
    "level": "T3",
    "type": "特殊兵装",
    "attrs": {
        "装填": {
            "初始": "14",
            "强化+10": "35",
            "强化+11": "38"
        },
        "炮击": {
            "初始": "3",
            "强化+10": "7",
            "强化+11": "8"
        },
        "大型作战塞壬增伤": {
            "备注": "强化+11后获得此属性",
            "强化+11": "1%"
        },
        "装备参数": {
            "所属阵营": "其他"
        }
    },
    "suit_type": [
        "驱逐",
        "轻巡",
        "重巡",
        "超巡",
        "战巡",
        "战列",
        "航战",
        "潜母",
        "重炮",
        "潜艇",
        "维修",
        "运输"
    ],
    "img_url": ""
}